README.rst
setup.py
nytcomments/__init__.py
nytcomments/dataprocessing.py
nytcomments/nytcomments.py
nytcomments.egg-info/PKG-INFO
nytcomments.egg-info/SOURCES.txt
nytcomments.egg-info/dependency_links.txt
nytcomments.egg-info/not-zip-safe
nytcomments.egg-info/requires.txt
nytcomments.egg-info/top_level.txt