Metadata-Version: 1.0
Name: nytcomments
Version: 0.1
Summary: Package to retrieve comments from the New York Time articles that also serves as API Wrapper for NYT article search and performs the function of the now deprecated NYT Community API
Home-page: https://github.com/AashitaK/nyt-comments
Author: Aashita Kesarwani
Author-email: kesar01@gmail.com
License: MIT
Keywords: Scraper for comments from the New York Time articles,API Wrapper for NYT API
Platform: UNKNOWN
